{
  "total_count": 3068,
  "runners": [
    {
      "id": 3843,
      "name": "arc-runnerset-25gfm-0",
      "os": "Linux",
      "status": "online",
      "busy": false,
      "labels": [
        {
          "id": 4,
          "name": "self-hosted",
          "type": "read-only"
        },
        {
          "id": 5,
          "name": "Linux",
          "type": "read-only"
        },
        {
          "id": 6,
          "name": "X64",
          "type": "read-only"
        },
        {
          "id": 8,
          "name": "api-gateway",
          "type": "custom"
        },
        {
          "id": 9,
          "name": "daeapigwgha02",
          "type": "custom"
        },
        {
          "id": 10,
          "name": "dae",
          "type": "custom"
        },
        {
          "id": 11,
          "name": "pr-handler-regular",
          "type": "custom"
        }
      ]
    },
    {
      "id": 3845,
      "name": "arc-runnerset-2n2gg-0",
      "os": "Linux",
      "status": "online",
      "busy": false,
      "labels": [
        {
          "id": 4,
          "name": "self-hosted",
          "type": "read-only"
        },
        {
          "id": 5,
          "name": "Linux",
          "type": "read-only"
        },
        {
          "id": 6,
          "name": "X64",
          "type": "read-only"
        },
        {
          "id": 8,
          "name": "api-gateway",
          "type": "custom"
        },
        {
          "id": 9,
          "name": "daeapigwgha02",
          "type": "custom"
        },
        {
          "id": 10,
          "name": "dae",
          "type": "custom"
        },
        {
          "id": 11,
          "name": "pr-handler-regular",
          "type": "custom"
        }
      ]
    },
    {
      "id": 170,
      "name": "arc-runnerset-2tjpr-0",
      "os": "Linux",
      "status": "online",
      "busy": false,
      "labels": [
        {
          "id": 4,
          "name": "self-hosted",
          "type": "read-only"
        },
        {
          "id": 5,
          "name": "Linux",
          "type": "read-only"
        },
        {
          "id": 6,
          "name": "X64",
          "type": "read-only"
        },
        {
          "id": 8,
          "name": "api-gateway",
          "type": "custom"
        },
        {
          "id": 11,
          "name": "pr-handler-regular",
          "type": "custom"
        },
        {
          "id": 14,
          "name": "chn",
          "type": "custom"
        },
        {
          "id": 16,
          "name": "vmnxapigwgha03",
          "type": "custom"
        }
      ]
    },
    {
      "id": 3840,
      "name": "arc-runnerset-49bhd-0",
      "os": "Linux",
      "status": "online",
      "busy": false,
      "labels": [
        {
          "id": 4,
          "name": "self-hosted",
          "type": "read-only"
        },
        {
          "id": 5,
          "name": "Linux",
          "type": "read-only"
        },
        {
          "id": 6,
          "name": "X64",
          "type": "read-only"
        },
        {
          "id": 8,
          "name": "api-gateway",
          "type": "custom"
        },
        {
          "id": 9,
          "name": "daeapigwgha02",
          "type": "custom"
        },
        {
          "id": 10,
          "name": "dae",
          "type": "custom"
        },
        {
          "id": 11,
          "name": "pr-handler-regular",
          "type": "custom"
        }
      ]
    },
    {
      "id": 171,
      "name": "arc-runnerset-4ltcd-0",
      "os": "Linux",
      "status": "online",
      "busy": false,
      "labels": [
        {
          "id": 4,
          "name": "self-hosted",
          "type": "read-only"
        },
        {
          "id": 5,
          "name": "Linux",
          "type": "read-only"
        },
        {
          "id": 6,
          "name": "X64",
          "type": "read-only"
        },
        {
          "id": 8,
          "name": "api-gateway",
          "type": "custom"
        },
        {
          "id": 11,
          "name": "pr-handler-regular",
          "type": "custom"
        },
        {
          "id": 14,
          "name": "chn",
          "type": "custom"
        },
        {
          "id": 16,
          "name": "vmnxapigwgha03",
          "type": "custom"
        }
      ]
    },
    {
      "id": 3846,
      "name": "arc-runnerset-6kmdz-0",
      "os": "Linux",
      "status": "online",
      "busy": false,
      "labels": [
        {
          "id": 4,
          "name": "self-hosted",
          "type": "read-only"
        },
        {
          "id": 5,
          "name": "Linux",
          "type": "read-only"
        },
        {
          "id": 6,
          "name": "X64",
          "type": "read-only"
        },
        {
          "id": 8,
          "name": "api-gateway",
          "type": "custom"
        },
        {
          "id": 9,
          "name": "daeapigwgha02",
          "type": "custom"
        },
        {
          "id": 10,
          "name": "dae",
          "type": "custom"
        },
        {
          "id": 11,
          "name": "pr-handler-regular",
          "type": "custom"
        }
      ]
    },
    {
      "id": 3841,
      "name": "arc-runnerset-7nvq8-0",
      "os": "Linux",
      "status": "online",
      "busy": false,
      "labels": [
        {
          "id": 4,
          "name": "self-hosted",
          "type": "read-only"
        },
        {
          "id": 5,
          "name": "Linux",
          "type": "read-only"
        },
        {
          "id": 6,
          "name": "X64",
          "type": "read-only"
        },
        {
          "id": 8,
          "name": "api-gateway",
          "type": "custom"
        },
        {
          "id": 9,
          "name": "daeapigwgha02",
          "type": "custom"
        },
        {
          "id": 10,
          "name": "dae",
          "type": "custom"
        },
        {
          "id": 11,
          "name": "pr-handler-regular",
          "type": "custom"
        }
      ]
    },
    {
      "id": 165,
      "name": "arc-runnerset-88wxx-0",
      "os": "Linux",
      "status": "online",
      "busy": false,
      "labels": [
        {
          "id": 4,
          "name": "self-hosted",
          "type": "read-only"
        },
        {
          "id": 5,
          "name": "Linux",
          "type": "read-only"
        },
        {
          "id": 6,
          "name": "X64",
          "type": "read-only"
        },
        {
          "id": 8,
          "name": "api-gateway",
          "type": "custom"
        },
        {
          "id": 11,
          "name": "pr-handler-regular",
          "type": "custom"
        },
        {
          "id": 14,
          "name": "chn",
          "type": "custom"
        },
        {
          "id": 15,
          "name": "vmnxapigwgha02",
          "type": "custom"
        }
      ]
    },
    {
      "id": 3844,
      "name": "arc-runnerset-g4f2k-0",
      "os": "Linux",
      "status": "online",
      "busy": false,
      "labels": [
        {
          "id": 4,
          "name": "self-hosted",
          "type": "read-only"
        },
        {
          "id": 5,
          "name": "Linux",
          "type": "read-only"
        },
        {
          "id": 6,
          "name": "X64",
          "type": "read-only"
        },
        {
          "id": 8,
          "name": "api-gateway",
          "type": "custom"
        },
        {
          "id": 10,
          "name": "dae",
          "type": "custom"
        },
        {
          "id": 12,
          "name": "daeapigwgha01",
          "type": "custom"
        },
        {
          "id": 13,
          "name": "pr-handler-high-config",
          "type": "custom"
        }
      ]
    },
    {
      "id": 769,
      "name": "arc-runnerset-gvt4j-0",
      "os": "Linux",
      "status": "online",
      "busy": false,
      "labels": [
        {
          "id": 4,
          "name": "self-hosted",
          "type": "read-only"
        },
        {
          "id": 5,
          "name": "Linux",
          "type": "read-only"
        },
        {
          "id": 6,
          "name": "X64",
          "type": "read-only"
        },
        {
          "id": 8,
          "name": "api-gateway",
          "type": "custom"
        },
        {
          "id": 10,
          "name": "dae",
          "type": "custom"
        },
        {
          "id": 12,
          "name": "daeapigwgha01",
          "type": "custom"
        },
        {
          "id": 13,
          "name": "pr-handler-high-config",
          "type": "custom"
        }
      ]
    },
    {
      "id": 164,
      "name": "arc-runnerset-mpwnz-0",
      "os": "Linux",
      "status": "online",
      "busy": false,
      "labels": [
        {
          "id": 4,
          "name": "self-hosted",
          "type": "read-only"
        },
        {
          "id": 5,
          "name": "Linux",
          "type": "read-only"
        },
        {
          "id": 6,
          "name": "X64",
          "type": "read-only"
        },
        {
          "id": 8,
          "name": "api-gateway",
          "type": "custom"
        },
        {
          "id": 11,
          "name": "pr-handler-regular",
          "type": "custom"
        },
        {
          "id": 14,
          "name": "chn",
          "type": "custom"
        },
        {
          "id": 15,
          "name": "vmnxapigwgha02",
          "type": "custom"
        }
      ]
    },
    {
      "id": 169,
      "name": "arc-runnerset-qwbdf-0",
      "os": "Linux",
      "status": "online",
      "busy": false,
      "labels": [
        {
          "id": 4,
          "name": "self-hosted",
          "type": "read-only"
        },
        {
          "id": 5,
          "name": "Linux",
          "type": "read-only"
        },
        {
          "id": 6,
          "name": "X64",
          "type": "read-only"
        },
        {
          "id": 8,
          "name": "api-gateway",
          "type": "custom"
        },
        {
          "id": 11,
          "name": "pr-handler-regular",
          "type": "custom"
        },
        {
          "id": 14,
          "name": "chn",
          "type": "custom"
        },
        {
          "id": 16,
          "name": "vmnxapigwgha03",
          "type": "custom"
        }
      ]
    },
    {
      "id": 3842,
      "name": "arc-runnerset-xmlr7-0",
      "os": "Linux",
      "status": "online",
      "busy": false,
      "labels": [
        {
          "id": 4,
          "name": "self-hosted",
          "type": "read-only"
        },
        {
          "id": 5,
          "name": "Linux",
          "type": "read-only"
        },
        {
          "id": 6,
          "name": "X64",
          "type": "read-only"
        },
        {
          "id": 8,
          "name": "api-gateway",
          "type": "custom"
        },
        {
          "id": 9,
          "name": "daeapigwgha02",
          "type": "custom"
        },
        {
          "id": 10,
          "name": "dae",
          "type": "custom"
        },
        {
          "id": 11,
          "name": "pr-handler-regular",
          "type": "custom"
        }
      ]
    },
    {
      "id": 166,
      "name": "arc-runnerset-z4s5j-0",
      "os": "Linux",
      "status": "online",
      "busy": false,
      "labels": [
        {
          "id": 4,
          "name": "self-hosted",
          "type": "read-only"
        },
        {
          "id": 5,
          "name": "Linux",
          "type": "read-only"
        },
        {
          "id": 6,
          "name": "X64",
          "type": "read-only"
        },
        {
          "id": 8,
          "name": "api-gateway",
          "type": "custom"
        },
        {
          "id": 11,
          "name": "pr-handler-regular",
          "type": "custom"
        },
        {
          "id": 14,
          "name": "chn",
          "type": "custom"
        },
        {
          "id": 15,
          "name": "vmnxapigwgha02",
          "type": "custom"
        }
      ]
    },
    {
      "id": 271,
      "name": "daeapigwgha01-vm",
      "os": "Linux",
      "status": "online",
      "busy": false,
      "labels": [
        {
          "id": 4,
          "name": "self-hosted",
          "type": "read-only"
        },
        {
          "id": 5,
          "name": "Linux",
          "type": "read-only"
        },
        {
          "id": 6,
          "name": "X64",
          "type": "read-only"
        },
        {
          "id": 20,
          "name": "daeapigwgha01-vm",
          "type": "custom"
        }
      ]
    },
    {
      "id": 10,
      "name": "daeyairunner01",
      "os": "Linux",
      "status": "online",
      "busy": false,
      "labels": [
        {
          "id": 4,
          "name": "self-hosted",
          "type": "read-only"
        },
        {
          "id": 5,
          "name": "Linux",
          "type": "read-only"
        },
        {
          "id": 6,
          "name": "X64",
          "type": "read-only"
        },
        {
          "id": 7,
          "name": "apigateway",
          "type": "custom"
        }
      ]
    },
    {
      "id": 11,
      "name": "daeyairunner02",
      "os": "Linux",
      "status": "online",
      "busy": false,
      "labels": [
        {
          "id": 4,
          "name": "self-hosted",
          "type": "read-only"
        },
        {
          "id": 5,
          "name": "Linux",
          "type": "read-only"
        },
        {
          "id": 6,
          "name": "X64",
          "type": "read-only"
        },
        {
          "id": 7,
          "name": "apigateway",
          "type": "custom"
        }
      ]
    },
    {
      "id": 2770,
      "name": "arc-runnerset-225rz-0",
      "os": "Linux",
      "status": "offline",
      "busy": false,
      "labels": [
        {
          "id": 4,
          "name": "self-hosted",
          "type": "read-only"
        },
        {
          "id": 5,
          "name": "Linux",
          "type": "read-only"
        },
        {
          "id": 6,
          "name": "X64",
          "type": "read-only"
        },
        {
          "id": 8,
          "name": "api-gateway",
          "type": "custom"
        },
        {
          "id": 14,
          "name": "chn",
          "type": "custom"
        },
        {
          "id": 21,
          "name": "vmnxapigwgha06",
          "type": "custom"
        },
        {
          "id": 22,
          "name": "ca3s-dev-handler",
          "type": "custom"
        }
      ]
    },
    {
      "id": 3014,
      "name": "arc-runnerset-22bnl-0",
      "os": "Linux",
      "status": "offline",
      "busy": false,
      "labels": [
        {
          "id": 4,
          "name": "self-hosted",
          "type": "read-only"
        },
        {
          "id": 5,
          "name": "Linux",
          "type": "read-only"
        },
        {
          "id": 6,
          "name": "X64",
          "type": "read-only"
        },
        {
          "id": 8,
          "name": "api-gateway",
          "type": "custom"
        },
        {
          "id": 14,
          "name": "chn",
          "type": "custom"
        },
        {
          "id": 21,
          "name": "vmnxapigwgha06",
          "type": "custom"
        },
        {
          "id": 22,
          "name": "ca3s-dev-handler",
          "type": "custom"
        }
      ]
    },
    {
      "id": 1355,
      "name": "arc-runnerset-22clt-0",
      "os": "Linux",
      "status": "offline",
      "busy": false,
      "labels": [
        {
          "id": 4,
          "name": "self-hosted",
          "type": "read-only"
        },
        {
          "id": 5,
          "name": "Linux",
          "type": "read-only"
        },
        {
          "id": 6,
          "name": "X64",
          "type": "read-only"
        },
        {
          "id": 8,
          "name": "api-gateway",
          "type": "custom"
        },
        {
          "id": 14,
          "name": "chn",
          "type": "custom"
        },
        {
          "id": 21,
          "name": "vmnxapigwgha06",
          "type": "custom"
        },
        {
          "id": 22,
          "name": "ca3s-dev-handler",
          "type": "custom"
        }
      ]
    },
    {
      "id": 800,
      "name": "arc-runnerset-22hn9-0",
      "os": "Linux",
      "status": "offline",
      "busy": false,
      "labels": [
        {
          "id": 4,
          "name": "self-hosted",
          "type": "read-only"
        },
        {
          "id": 5,
          "name": "Linux",
          "type": "read-only"
        },
        {
          "id": 6,
          "name": "X64",
          "type": "read-only"
        },
        {
          "id": 8,
          "name": "api-gateway",
          "type": "custom"
        },
        {
          "id": 14,
          "name": "chn",
          "type": "custom"
        },
        {
          "id": 21,
          "name": "vmnxapigwgha06",
          "type": "custom"
        },
        {
          "id": 22,
          "name": "ca3s-dev-handler",
          "type": "custom"
        }
      ]
    },
    {
      "id": 2693,
      "name": "arc-runnerset-22vgc-0",
      "os": "Linux",
      "status": "offline",
      "busy": false,
      "labels": [
        {
          "id": 4,
          "name": "self-hosted",
          "type": "read-only"
        },
        {
          "id": 5,
          "name": "Linux",
          "type": "read-only"
        },
        {
          "id": 6,
          "name": "X64",
          "type": "read-only"
        },
        {
          "id": 8,
          "name": "api-gateway",
          "type": "custom"
        },
        {
          "id": 14,
          "name": "chn",
          "type": "custom"
        },
        {
          "id": 21,
          "name": "vmnxapigwgha06",
          "type": "custom"
        },
        {
          "id": 22,
          "name": "ca3s-dev-handler",
          "type": "custom"
        }
      ]
    },
    {
      "id": 1639,
      "name": "arc-runnerset-22w8j-0",
      "os": "Linux",
      "status": "offline",
      "busy": false,
      "labels": [
        {
          "id": 4,
          "name": "self-hosted",
          "type": "read-only"
        },
        {
          "id": 5,
          "name": "Linux",
          "type": "read-only"
        },
        {
          "id": 6,
          "name": "X64",
          "type": "read-only"
        },
        {
          "id": 8,
          "name": "api-gateway",
          "type": "custom"
        },
        {
          "id": 14,
          "name": "chn",
          "type": "custom"
        },
        {
          "id": 21,
          "name": "vmnxapigwgha06",
          "type": "custom"
        },
        {
          "id": 22,
          "name": "ca3s-dev-handler",
          "type": "custom"
        }
      ]
    },
    {
      "id": 2254,
      "name": "arc-runnerset-2492n-0",
      "os": "Linux",
      "status": "offline",
      "busy": false,
      "labels": [
        {
          "id": 4,
          "name": "self-hosted",
          "type": "read-only"
        },
        {
          "id": 5,
          "name": "Linux",
          "type": "read-only"
        },
        {
          "id": 6,
          "name": "X64",
          "type": "read-only"
        },
        {
          "id": 8,
          "name": "api-gateway",
          "type": "custom"
        },
        {
          "id": 14,
          "name": "chn",
          "type": "custom"
        },
        {
          "id": 21,
          "name": "vmnxapigwgha06",
          "type": "custom"
        },
        {
          "id": 22,
          "name": "ca3s-dev-handler",
          "type": "custom"
        }
      ]
    },
    {
      "id": 2035,
      "name": "arc-runnerset-24rkq-0",
      "os": "Linux",
      "status": "offline",
      "busy": false,
      "labels": [
        {
          "id": 4,
          "name": "self-hosted",
          "type": "read-only"
        },
        {
          "id": 5,
          "name": "Linux",
          "type": "read-only"
        },
        {
          "id": 6,
          "name": "X64",
          "type": "read-only"
        },
        {
          "id": 8,
          "name": "api-gateway",
          "type": "custom"
        },
        {
          "id": 14,
          "name": "chn",
          "type": "custom"
        },
        {
          "id": 21,
          "name": "vmnxapigwgha06",
          "type": "custom"
        },
        {
          "id": 22,
          "name": "ca3s-dev-handler",
          "type": "custom"
        }
      ]
    },
    {
      "id": 3083,
      "name": "arc-runnerset-254pp-0",
      "os": "Linux",
      "status": "offline",
      "busy": false,
      "labels": [
        {
          "id": 4,
          "name": "self-hosted",
          "type": "read-only"
        },
        {
          "id": 5,
          "name": "Linux",
          "type": "read-only"
        },
        {
          "id": 6,
          "name": "X64",
          "type": "read-only"
        },
        {
          "id": 8,
          "name": "api-gateway",
          "type": "custom"
        },
        {
          "id": 14,
          "name": "chn",
          "type": "custom"
        },
        {
          "id": 21,
          "name": "vmnxapigwgha06",
          "type": "custom"
        },
        {
          "id": 22,
          "name": "ca3s-dev-handler",
          "type": "custom"
        }
      ]
    },
    {
      "id": 1910,
      "name": "arc-runnerset-254zj-0",
      "os": "Linux",
      "status": "offline",
      "busy": false,
      "labels": [
        {
          "id": 4,
          "name": "self-hosted",
          "type": "read-only"
        },
        {
          "id": 5,
          "name": "Linux",
          "type": "read-only"
        },
        {
          "id": 6,
          "name": "X64",
          "type": "read-only"
        },
        {
          "id": 8,
          "name": "api-gateway",
          "type": "custom"
        },
        {
          "id": 14,
          "name": "chn",
          "type": "custom"
        },
        {
          "id": 21,
          "name": "vmnxapigwgha06",
          "type": "custom"
        },
        {
          "id": 22,
          "name": "ca3s-dev-handler",
          "type": "custom"
        }
      ]
    },
    {
      "id": 3685,
      "name": "arc-runnerset-25bcd-0",
      "os": "Linux",
      "status": "offline",
      "busy": false,
      "labels": [
        {
          "id": 4,
          "name": "self-hosted",
          "type": "read-only"
        },
        {
          "id": 5,
          "name": "Linux",
          "type": "read-only"
        },
        {
          "id": 6,
          "name": "X64",
          "type": "read-only"
        },
        {
          "id": 8,
          "name": "api-gateway",
          "type": "custom"
        },
        {
          "id": 14,
          "name": "chn",
          "type": "custom"
        },
        {
          "id": 21,
          "name": "vmnxapigwgha06",
          "type": "custom"
        },
        {
          "id": 22,
          "name": "ca3s-dev-handler",
          "type": "custom"
        }
      ]
    },
    {
      "id": 1446,
      "name": "arc-runnerset-25jqt-0",
      "os": "Linux",
      "status": "offline",
      "busy": false,
      "labels": [
        {
          "id": 4,
          "name": "self-hosted",
          "type": "read-only"
        },
        {
          "id": 5,
          "name": "Linux",
          "type": "read-only"
        },
        {
          "id": 6,
          "name": "X64",
          "type": "read-only"
        },
        {
          "id": 8,
          "name": "api-gateway",
          "type": "custom"
        },
        {
          "id": 14,
          "name": "chn",
          "type": "custom"
        },
        {
          "id": 21,
          "name": "vmnxapigwgha06",
          "type": "custom"
        },
        {
          "id": 22,
          "name": "ca3s-dev-handler",
          "type": "custom"
        }
      ]
    },
    {
      "id": 1686,
      "name": "arc-runnerset-25w4q-0",
      "os": "Linux",
      "status": "offline",
      "busy": false,
      "labels": [
        {
          "id": 4,
          "name": "self-hosted",
          "type": "read-only"
        },
        {
          "id": 5,
          "name": "Linux",
          "type": "read-only"
        },
        {
          "id": 6,
          "name": "X64",
          "type": "read-only"
        },
        {
          "id": 8,
          "name": "api-gateway",
          "type": "custom"
        },
        {
          "id": 14,
          "name": "chn",
          "type": "custom"
        },
        {
          "id": 21,
          "name": "vmnxapigwgha06",
          "type": "custom"
        },
        {
          "id": 22,
          "name": "ca3s-dev-handler",
          "type": "custom"
        }
      ]
    }
  ]
}
